swift_portal_downloader/__init__.py
swift_portal_downloader/comet_db/__init__.py
swift_portal_downloader/comet_db/comet_db.py
swift_portal_downloader/comet_db/comet_db_search.py
swift_portal_downloader/comet_db/download_comet_db.py
swift_portal_downloader/config/__init__.py
swift_portal_downloader/config/spd_config.py
swift_portal_downloader/naming/__init__.py
swift_portal_downloader/naming/canonical_comet_name.py
swift_portal_downloader/naming/manual_renaming.py
swift_portal_downloader/naming/manual_renaming_scheme.py
swift_portal_downloader/naming/name_conversion.py
swift_portal_downloader/naming/swift_target_name_to_canonical_name.yaml
swift_portal_downloader/portal/__init__.py
swift_portal_downloader/portal/download/__init__.py
swift_portal_downloader/portal/download/download_comet_db_entry.py
swift_portal_downloader/portal/download/observation_id_to_wget_command.py
swift_portal_downloader/portal/download/target_id_to_observation_id.py
swift_portal_downloader/portal/download/uncompressed_download.py
swift_portal_downloader/portal/download/wget_command.py
swift_portal_downloader/portal/search/__init__.py
swift_portal_downloader/portal/search/all_comet_search.py
swift_portal_downloader/portal/search/search_by_name.py
swift_portal_downloader/swift/__init__.py
swift_portal_downloader/swift/swift_downloadable_data_types.py
swift_portal_downloader/swift/swift_observation_id.py
swift_portal_downloader/swift/swift_target_id.py
swift_portal_downloader/swift/swift_target_name.py
swift_portal_downloader/tui/__init__.py
swift_portal_downloader/tui/create_config_tui.py
swift_portal_downloader/tui/download_comet_db_tui.py
swift_portal_downloader/tui/download_comet_tui.py
swift_portal_downloader/tui/rich_display.py
swift_portal_downloader/tui/search_comet_db_tui.py
swift_portal_downloader/tui/show_info_tui.py
swift_portal_downloader/tui/spd_tui.py
swift_portal_downloader/tui/tui_info.md
swift_portal_downloader-0.1.0.dist-info/LICENSE
swift_portal_downloader-0.1.0.dist-info/METADATA
swift_portal_downloader-0.1.0.dist-info/WHEEL
swift_portal_downloader-0.1.0.dist-info/entry_points.txt
swift_portal_downloader-0.1.0.dist-info/RECORD
