Metadata-Version: 2.1
Name: swift_portal_downloader
Version: 0.1.0
Summary: Project to search and download swift comet images from the dead portal at https://www.swift.ac.uk/dead_portal
License: LICENSE
Author: Jacob Duffy
Requires-Python: >=3.11,<3.13
Classifier: License :: Other/Proprietary License
Classifier: Programming Language :: Python :: 3
Classifier: Programming Language :: Python :: 3.11
Classifier: Programming Language :: Python :: 3.12
Requires-Dist: beautifulsoup4 (>=4.12.3,<5.0.0)
Requires-Dist: lxml (>=5.1.0,<6.0.0)
Requires-Dist: numpy (>=1.26.4,<2.0.0)
Requires-Dist: pandas (>=2.2.0,<3.0.0)
Requires-Dist: pyyaml (>=6.0.1,<7.0.0)
Requires-Dist: questionary (>=2.0.1,<3.0.0)
Requires-Dist: requests (>=2.31.0,<3.0.0)
Requires-Dist: rich (>=13.7.0,<14.0.0)
